hamux/__init__.py
hamux/core.py
hamux/lagrangians.py
hamux-0.2.2.dist-info/METADATA
hamux-0.2.2.dist-info/WHEEL
hamux-0.2.2.dist-info/licenses/LICENSE
hamux-0.2.2.dist-info/RECORD
