Metadata-Version: 2.4
Name: hamux
Version: 0.2.2
Summary: Add your description here
Author-email: Ben Hoover <24350185+bhoov@users.noreply.github.com>
License-File: LICENSE
Requires-Python: >=3.10
Requires-Dist: equinox>=0.12.2
Requires-Dist: jax>=0.6.1
